deduckprover/__init__.py
deduckprover/main.py
deduckprover/parser.py
deduckprover/rules.py
deduckprover/script.py
deduckprover/syntax.py
deduckprover/utils.py
deduckprover/verifier.py
deduckprover/vscode.py
deduck_prover-0.2.2.data/data/LICENSE
deduck_prover-0.2.2.data/data/README.md
deduck_prover-0.2.2.dist-info/METADATA
deduck_prover-0.2.2.dist-info/WHEEL
deduck_prover-0.2.2.dist-info/entry_points.txt
deduck_prover-0.2.2.dist-info/licenses/LICENSE
deduck_prover-0.2.2.dist-info/RECORD
