Metadata-Version: 2.4
Name: deduck-prover
Version: 0.2.2
Summary: A little prover for CS 245 at the University of Waterloo
Project-URL: Repository, https://github.com/deduck-prover/deduck.git
Author: Yizhou Zhang
License-Expression: MIT
License-File: LICENSE
Classifier: Development Status :: 4 - Beta
Classifier: Intended Audience :: Education
Classifier: Intended Audience :: Science/Research
Classifier: License :: OSI Approved :: MIT License
Classifier: Operating System :: OS Independent
Classifier: Programming Language :: Python :: 3
Classifier: Programming Language :: Python :: 3.7
Classifier: Topic :: Education
Classifier: Topic :: Scientific/Engineering :: Mathematics
Requires-Python: >=3.7
Requires-Dist: lark>=0.12.0
